// Generated by javap -v -c Add > Add.javap.txt
Classfile Add.class
  Last modified Jul 6, 2020; size 236 bytes
  MD5 checksum af99405b19b838f9943ae7c377b27c43
  Compiled from "Add.java"
public class Add
  minor version: 0
  major version: 55
  flags: (0x0021) ACC_PUBLIC, ACC_SUPER
  this_class: #2                          // Add
  super_class: #3                         // java/lang/Object
  interfaces: 0, fields: 0, methods: 2, attributes: 1
Constant pool:
   #1 = Methodref          #3.#12         // java/lang/Object."<init>":()V
   #2 = Class              #13            // Add
   #3 = Class              #14            // java/lang/Object
   #4 = Utf8               <init>
   #5 = Utf8               ()V
   #6 = Utf8               Code
   #7 = Utf8               LineNumberTable
   #8 = Utf8               add
   #9 = Utf8               (II)I
  #10 = Utf8               SourceFile
  #11 = Utf8               Add.java
  #12 = NameAndType        #4:#5          // "<init>":()V
  #13 = Utf8               Add
  #14 = Utf8               java/lang/Object
{
  public Add();
    descriptor: ()V
    flags: (0x0001) ACC_PUBLIC
    Code:
      stack=1, locals=1, args_size=1
         0: aload_0
         1: invokespecial #1                  // Method java/lang/Object."<init>":()V
         4: return
      LineNumberTable:
        line 1: 0

  public static int add(int, int);
    descriptor: (II)I
    flags: (0x0009) ACC_PUBLIC, ACC_STATIC
    Code:
      stack=2, locals=2, args_size=2
         0: iload_0
         1: iload_1
         2: iadd
         3: ireturn
      LineNumberTable:
        line 3: 0
}
SourceFile: "Add.java"
